MAxPy/__init__.py
MAxPy/check.py
MAxPy/compile.py
MAxPy/estimations.py
MAxPy/maxpy.py
MAxPy/pareto.py
MAxPy/probprun.py
MAxPy/resources.py
MAxPy/results.py
MAxPy/synth.py
MAxPy/utility.py
MAxPy/verilate.py
MAxPy/wrapper.py
MAxPy/pdk/NanGate15nm.lib
MAxPy/pdk/NanGate15nm.v
MAxPy/tcl/Genus/constraints.sdc
MAxPy/tcl/Genus/qor_saif.tcl
MAxPy/tcl/Genus/qor_sta.tcl
MAxPy/tcl/Genus/sdf_cmd_file.base
MAxPy/tcl/Genus/sta.tcl
MAxPy/tcl/Genus/synth.tcl
MAxPy/tcl/Incisive/tcf_cmd.tcl
MAxPy/tcl/OpenSTA/cmd_file.sta
MAxPy/tcl/Verilator/verilator_config.vlt
MAxPy/tcl/Yosys/synth.ys
MAxPy/templates/cmake_pybind.txt
MAxPy/templates/instance_source.cpp
MAxPy/templates/verilator_pybind_wrapper.cpp
MAxPy/templates/verilator_pybind_wrapper.h
MAxPy/vlib/AxArith/README.md
MAxPy/vlib/AxArith/adders/copy.v
MAxPy/vlib/AxArith/adders/eta1.v
MAxPy/vlib/AxArith/adders/loa.v
MAxPy/vlib/AxArith/adders/trunc.v
MAxPy/vlib/AxArith/multipliers/DRUM.v
MAxPy/vlib/AxArith/multipliers/LOBA.v
MAxPy-0.1.2.dist-info/LICENSE
MAxPy-0.1.2.dist-info/METADATA
MAxPy-0.1.2.dist-info/WHEEL
MAxPy-0.1.2.dist-info/top_level.txt
MAxPy-0.1.2.dist-info/RECORD
