Metadata-Version: 2.1
Name: MAxPy
Version: 0.1.2
Summary: Multi-layer Approximate Computing Python Framework
Home-page: https://maxpy-project.github.io/MAxPy/
Author: Yuri Arbeletche <ysba000@gmail.com>, Guilherme Paim <gppaim@ieee.org>
Project-URL: Bug Tracker, https://github.com/MAxPy-Project/MAxPy/issues
Classifier: Programming Language :: Python :: 3
Classifier: License :: OSI Approved :: GNU Lesser General Public License v3 (LGPLv3)
Classifier: Operating System :: OS Independent
Requires-Python: >=3.9
License-File: LICENSE
Requires-Dist: pandas
Requires-Dist: matplotlib
